{
  "db_name": "PostgreSQL",
  "query": "\n        SELECT id, thread_id, \"order\", owner, sender, text, metadata,\n               created_at, updated_at, deleted_at\n        FROM crm_comment\n        WHERE thread_id = ANY($1) AND deleted_at IS NULL\n        ORDER BY created_at ASC, id ASC\n        ",
  "describe": {
    "columns": [
      {
        "ordinal": 0,
        "name": "id",
        "type_info": "Uuid"
      },
      {
        "ordinal": 1,
        "name": "thread_id",
        "type_info": "Uuid"
      },
      {
        "ordinal": 2,
        "name": "order",
        "type_info": "Int4"
      },
      {
        "ordinal": 3,
        "name": "owner",
        "type_info": "Text"
      },
      {
        "ordinal": 4,
        "name": "sender",
        "type_info": "Text"
      },
      {
        "ordinal": 5,
        "name": "text",
        "type_info": "Text"
      },
      {
        "ordinal": 6,
        "name": "metadata",
        "type_info": "Jsonb"
      },
      {
        "ordinal": 7,
        "name": "created_at",
        "type_info": "Timestamptz"
      },
      {
        "ordinal": 8,
        "name": "updated_at",
        "type_info": "Timestamptz"
      },
      {
        "ordinal": 9,
        "name": "deleted_at",
        "type_info": "Timestamptz"
      }
    ],
    "parameters": {
      "Left": [
        "UuidArray"
      ]
    },
    "nullable": [
      false,
      false,
      true,
      false,
      true,
      false,
      true,
      false,
      false,
      true
    ]
  },
  "hash": "582f4f2d5a5e9c72835d0a043f743a94d927a08a81b8687714a96bd52a94cfcf"
}
