{
  "db_name": "PostgreSQL",
  "query": "\n        SELECT\n            p.id,\n            p.name,\n            p.\"userId\" as \"owner\",\n            p.\"parentId\" as \"parent_id\",\n            p.\"createdAt\"::timestamptz as \"created_at!\",\n            p.\"updatedAt\"::timestamptz as \"updated_at!\"\n        FROM\n            \"Project\" p\n        WHERE\n            p.id = $1 AND p.\"deletedAt\" IS NULL\n        ",
  "describe": {
    "columns": [
      {
        "ordinal": 0,
        "name": "id",
        "type_info": "Text"
      },
      {
        "ordinal": 1,
        "name": "name",
        "type_info": "Text"
      },
      {
        "ordinal": 2,
        "name": "owner",
        "type_info": "Text"
      },
      {
        "ordinal": 3,
        "name": "parent_id",
        "type_info": "Text"
      },
      {
        "ordinal": 4,
        "name": "created_at!",
        "type_info": "Timestamptz"
      },
      {
        "ordinal": 5,
        "name": "updated_at!",
        "type_info": "Timestamptz"
      }
    ],
    "parameters": {
      "Left": [
        "Text"
      ]
    },
    "nullable": [
      false,
      false,
      false,
      true,
      null,
      null
    ]
  },
  "hash": "3e259ea5cbdcfae4334cb0125de6423fa95a0c127fbeba0a59d7096b0177c072"
}
