{
  "db_name": "PostgreSQL",
  "query": "\n        SELECT message_id, send_time\n        FROM email_scheduled_messages\n        WHERE message_id = ANY($1) AND sent = false\n        ",
  "describe": {
    "columns": [
      {
        "ordinal": 0,
        "name": "message_id",
        "type_info": "Uuid"
      },
      {
        "ordinal": 1,
        "name": "send_time",
        "type_info": "Timestamptz"
      }
    ],
    "parameters": {
      "Left": [
        "UuidArray"
      ]
    },
    "nullable": [
      false,
      false
    ]
  },
  "hash": "29496c090bdffe2b771ad704687525136fcd17a1d3e680142e5d0f9e253af578"
}
